pyrbd3/__init__.py
pyrbd3/datasets.py
pyrbd3/evaluator.py
pyrbd3/utils.py
pyrbd3/_core/CMakeLists.txt
pyrbd3/_core/__init__.py
pyrbd3/_core/bindings.cpp
pyrbd3/_core/common.cpp
pyrbd3/_core/mcs.cpp
pyrbd3/_core/pathset.cpp
pyrbd3/_core/pyrbd3_cpp.cpython-39-x86_64-linux-gnu.so
pyrbd3/_core/sdp.cpp
pyrbd3/_core/utils.cpp
pyrbd3/_core/include/pyrbd3/common.hpp
pyrbd3/_core/include/pyrbd3/mcs.hpp
pyrbd3/_core/include/pyrbd3/pathset.hpp
pyrbd3/_core/include/pyrbd3/sdp.hpp
pyrbd3/_core/include/pyrbd3/utils.hpp
pyrbd3/algorithms/__init__.py
pyrbd3/algorithms/availability/__init__.py
pyrbd3/algorithms/availability/engine.py
pyrbd3/algorithms/availability/mcs.py
pyrbd3/algorithms/availability/path.py
pyrbd3/algorithms/availability/pyrbd.py
pyrbd3/algorithms/availability/sdp.py
pyrbd3/algorithms/sets/__init__.py
pyrbd3/algorithms/sets/cutsets.py
pyrbd3/algorithms/sets/pathsets.py
pyrbd3.libs/libgomp-a34b3233.so.1.0.0
pyrbd3-0.1.2.post1.dist-info/METADATA
pyrbd3-0.1.2.post1.dist-info/WHEEL
pyrbd3-0.1.2.post1.dist-info/RECORD
pyrbd3-0.1.2.post1.dist-info/licenses/LICENSE
