Metadata-Version: 2.2
Name: pyrbd3
Version: 0.1.2.post1
Summary: Fast Reliability Block Diagram Evaluation Tool
Keywords: RBD,reliability,MCS,pybind11,C++
Author-Email: Shakthivelu Janardhanan <shakthivelu.janardhanan@tum.de>, Yaxuan Chen <yaxuan.chen@tum.de>
License: MIT License
Project-URL: Homepage, https://github.com/shakthij98/PyRBD3
Requires-Python: >=3.8
Requires-Dist: pandas
Requires-Dist: networkx
Requires-Dist: tqdm
Requires-Dist: loguru
